uplang/__init__.py
uplang/cli.py
uplang/commands/__init__.py
uplang/commands/base.py
uplang/commands/check.py
uplang/commands/init.py
uplang/config.py
uplang/container.py
uplang/core/extractor.py
uplang/core/scanner.py
uplang/core/state.py
uplang/core/synchronizer.py
uplang/exceptions.py
uplang/json_utils.py
uplang/logger.py
uplang/models.py
uplang/resources.py
uplang/utils.py
uplang/version.py
uplang-0.2.7.dist-info/WHEEL
uplang-0.2.7.dist-info/entry_points.txt
uplang-0.2.7.dist-info/METADATA
uplang-0.2.7.dist-info/RECORD
