Metadata-Version: 2.3
Name: uplang
Version: 0.2.7
Summary: A command-line tool to streamline the process of updating language files for Minecraft Java Edition modpacks.
Author: QianFuv
Author-email: QianFuv <qianfuv@qq.com>
License: Copyright <2025> <QianFuv>
Requires-Dist: click>=8.1.7
Requires-Dist: rich>=13.7.0
Requires-Dist: typer>=0.9.0
Requires-Dist: pytest>=8.2.2 ; extra == 'dev'
Requires-Dist: pytest-cov>=4.0.0 ; extra == 'dev'
Requires-Dist: pytest-mock>=3.12.0 ; extra == 'dev'
Requires-Python: >=3.11
Project-URL: Repository, https://github.com/QianFuv/UpLang
Provides-Extra: dev
